README.rst
setup.cfg
setup.py
splitviewfuse/LoggingUtils.py
splitviewfuse/SegmentUtils.py
splitviewfuse/SplitViewFuse.py
splitviewfuse/SplitViewFuseBase.py
splitviewfuse/UnionViewFuse.py
splitviewfuse/__init__.py
splitviewfuse.egg-info/PKG-INFO
splitviewfuse.egg-info/SOURCES.txt
splitviewfuse.egg-info/dependency_links.txt
splitviewfuse.egg-info/entry_points.txt
splitviewfuse.egg-info/requires.txt
splitviewfuse.egg-info/top_level.txt
splitviewfuse/filehandlecontainers/FileHandleContainer.py
splitviewfuse/filehandlecontainers/VirtualFileSegmentFileHandleContainer.py
splitviewfuse/filehandlecontainers/VirtualRegularFileFileHandleContainer.py
splitviewfuse/filehandlecontainers/__init__.py
splitviewfuse/virtualfiles/VirtualFile.py
splitviewfuse/virtualfiles/VirtualFileSegment.py
splitviewfuse/virtualfiles/VirtualRegularFile.py
splitviewfuse/virtualfiles/__init__.py