Metadata-Version: 1.1
Name: splitviewfuse
Version: 0.3.1
Summary: A fuse implementation for an segmented view on a given directory.
Home-page: https://github.com/seiferma/splitviewfuse
Author: Stephan Seifermann
Author-email: seiferma@t-online.de
License: MIT
Keywords: fuse view split segments
Platform: UNKNOWN
Classifier: Development Status :: 5 - Production/Stable
Classifier: Environment :: No Input/Output (Daemon)
Classifier: Intended Audience :: System Administrators
Classifier: Topic :: System :: Filesystems
Classifier: License :: OSI Approved :: MIT License
Classifier: Operating System :: MacOS :: MacOS X
Classifier: Operating System :: POSIX :: BSD :: FreeBSD
Classifier: Operating System :: POSIX :: Linux
Classifier: Programming Language :: Python :: 2.7
